{
    "snippet": {
        "2310000": {
            "timestamp": 1327774013.965076, 
            "secret": "gbqIEwMmLwHFmChT"
        }, 
        "2280000": {
            "timestamp": 1327774013.965076, 
            "secret": "gtVedQaNHtgaRuHw"
        }, 
        "2580000": {
            "timestamp": 1327773831.719473, 
            "secret": "EBUEUHubJfLXNATa"
        }
    }, 
    "review": {
        "2280000": {
            "timestamp": 1327774013.965076, 
            "secret": "VNOSWvkZnbzSbbLk"
        }
    }
}